GTool/api.py
GTool/config_api.py
GTool/generate_target.py
GToolGenerator-1.6.1.dist-info/LICENSE
GToolGenerator-1.6.1.dist-info/METADATA
GToolGenerator-1.6.1.dist-info/WHEEL
GToolGenerator-1.6.1.dist-info/top_level.txt
GToolGenerator-1.6.1.dist-info/RECORD
