Metadata-Version: 2.1
Name: GToolGenerator
Version: 1.6.1
Summary: Generate cards with useful data from different applications (for now only GitHub) and insert them in your web/app or wherever you want c: (API APP) 🎯
Home-page: https://github.com/ElHaban3ro/ConvTool
Author: ElHaban3ro
Author-email: habanferd@gmail.com
License: MIT
Keywords: GitHub,Generator,Target,Pillow
Classifier: Programming Language :: Python :: 3.10
License-File: LICENSE
Requires-Dist: requests
Requires-Dist: Pillow
Requires-Dist: beatifulsoup4
Requires-Dist: lxml
Requires-Dist: Flask
